ovos_skill_days_in_history/LICENSE
ovos_skill_days_in_history/README.md
ovos_skill_days_in_history/__init__.py
ovos_skill_days_in_history/version.py
ovos_skill_days_in_history/locale/en-us/TellMeMore.voc
ovos_skill_days_in_history/locale/en-us/births_in_history.intent
ovos_skill_days_in_history/locale/en-us/day_10_month_10_births.dialog
ovos_skill_days_in_history/locale/en-us/day_10_month_10_deaths.dialog
ovos_skill_days_in_history/locale/en-us/day_10_month_10_events.dialog
ovos_skill_days_in_history/locale/en-us/day_10_month_11_births.dialog
ovos_skill_days_in_history/locale/en-us/day_10_month_11_deaths.dialog
ovos_skill_days_in_history/locale/en-us/day_10_month_11_events.dialog
ovos_skill_days_in_history/locale/en-us/day_10_month_12_births.dialog
ovos_skill_days_in_history/locale/en-us/day_10_month_12_deaths.dialog
ovos_skill_days_in_history/locale/en-us/day_10_month_12_events.dialog
ovos_skill_days_in_history/locale/en-us/day_10_month_1_births.dialog
ovos_skill_days_in_history/locale/en-us/day_10_month_1_deaths.dialog
ovos_skill_days_in_history/locale/en-us/day_10_month_1_events.dialog
ovos_skill_days_in_history/locale/en-us/day_10_month_2_births.dialog
ovos_skill_days_in_history/locale/en-us/day_10_month_2_deaths.dialog
ovos_skill_days_in_history/locale/en-us/day_10_month_2_events.dialog
ovos_skill_days_in_history/locale/en-us/day_10_month_3_births.dialog
ovos_skill_days_in_history/locale/en-us/day_10_month_3_deaths.dialog
ovos_skill_days_in_history/locale/en-us/day_10_month_3_events.dialog
ovos_skill_days_in_history/locale/en-us/day_10_month_4_births.dialog
ovos_skill_days_in_history/locale/en-us/day_10_month_4_deaths.dialog
ovos_skill_days_in_history/locale/en-us/day_10_month_4_events.dialog
ovos_skill_days_in_history/locale/en-us/day_10_month_5_births.dialog
ovos_skill_days_in_history/locale/en-us/day_10_month_5_deaths.dialog
ovos_skill_days_in_history/locale/en-us/day_10_month_5_events.dialog
ovos_skill_days_in_history/ovos_skill_days_in_history.egg-info/PKG-INFO
ovos_skill_days_in_history/ovos_skill_days_in_history.egg-info/SOURCES.txt
ovos_skill_days_in_history/ovos_skill_days_in_history.egg-info/dependency_links.txt
ovos_skill_days_in_history/ovos_skill_days_in_history.egg-info/entry_points.txt
ovos_skill_days_in_history/ovos_skill_days_in_history.egg-info/requires.txt
ovos_skill_days_in_history/ovos_skill_days_in_history.egg-info/top_level.txt
ovos_skill_days_in_history-0.3.1.dist-info/LICENSE
ovos_skill_days_in_history-0.3.1.dist-info/METADATA
ovos_skill_days_in_history-0.3.1.dist-info/WHEEL
ovos_skill_days_in_history-0.3.1.dist-info/entry_points.txt
ovos_skill_days_in_history-0.3.1.dist-info/top_level.txt
ovos_skill_days_in_history-0.3.1.dist-info/RECORD
